[
  {
    "fullName": "Kenneth Levy",
    "country": "Brazil",
    "position": "Goalkeeper",
    "goals": 2,
    "assists": 1,
    "appearances": 28,
    "number": 1
  },
  {
    "fullName": "Audra Armstrong",
    "country": "France",
    "position": "Goalkeeper",
    "goals": 3,
    "assists": 5,
    "appearances": 35,
    "number": 42
  },
  {
    "fullName": "Indira Horton",
    "country": "Pakistan",
    "position": "Goalkeeper",
    "goals": 3,
    "assists": 2,
    "appearances": 34,
    "number": 45
  },
  {
    "fullName": "Zephania Bentley",
    "country": "United Kingdom",
    "position": "Goalkeeper",
    "goals": 2,
    "assists": 3,
    "appearances": 3,
    "number": 85
  },
  {
    "fullName": "Chava Cooke",
    "country": "Peru",
    "position": "Defender",
    "goals": 1,
    "assists": 5,
    "appearances": 25,
    "number": 79
  },
  {
    "fullName": "Maxine Wilkinson",
    "country": "United States",
    "position": "Defender",
    "goals": 1,
    "assists": 5,
    "appearances": 34,
    "number": 77
  },
  {
    "fullName": "Selma Spencer",
    "country": "United States",
    "position": "Defender",
    "goals": 1,
    "assists": 3,
    "appearances": 30,
    "number": 10
  },
  {
    "fullName": "Valentine Adams",
    "country": "Germany",
    "position": "Defender",
    "goals": 2,
    "assists": 2,
    "appearances": 7,
    "number": 37
  },
  {
    "fullName": "Nehru Greer",
    "country": "Austria",
    "position": "Defender",
    "goals": 1,
    "assists": 2,
    "appearances": 17,
    "number": 33
  },
  {
    "fullName": "Chaim Lyons",
    "country": "Russian Federation",
    "position": "Defender",
    "goals": 3,
    "assists": 2,
    "appearances": 15,
    "number": 18
  },
  {
    "fullName": "Raphael Holmes",
    "country": "Spain",
    "position": "Defender",
    "goals": 1,
    "assists": 4,
    "appearances": 8,
    "number": 46
  },
  {
    "fullName": "Winifred Carpenter",
    "country": "Canada",
    "position": "Defender",
    "goals": 2,
    "assists": 4,
    "appearances": 32,
    "number": 30
  },
  {
    "fullName": "Tatyana Owen",
    "country": "Pakistan",
    "position": "Midfielder",
    "goals": 1,
    "assists": 1,
    "appearances": 28,
    "number": 52
  },
  {
    "fullName": "Katell George",
    "country": "Germany",
    "position": "Midfielder",
    "goals": 0,
    "assists": 5,
    "appearances": 7,
    "number": 86
  },
  {
    "fullName": "Victor Pitts",
    "country": "South Korea",
    "position": "Midfielder",
    "goals": 0,
    "assists": 3,
    "appearances": 7,
    "number": 39
  },
  {
    "fullName": "Palmer Humphrey",
    "country": "Pakistan",
    "position": "Midfielder",
    "goals": 2,
    "assists": 2,
    "appearances": 3,
    "number": 49
  },
  {
    "fullName": "Judah Strickland",
    "country": "United States",
    "position": "Midfielder",
    "goals": 3,
    "assists": 1,
    "appearances": 25,
    "number": 1
  },
  {
    "fullName": "Lillian Mcclure",
    "country": "Pakistan",
    "position": "Midfielder",
    "goals": 1,
    "assists": 5,
    "appearances": 27,
    "number": 89
  },
  {
    "fullName": "Hunter Wall",
    "country": "Nigeria",
    "position": "Midfielder",
    "goals": 1,
    "assists": 5,
    "appearances": 8,
    "number": 19
  },
  {
    "fullName": "Roth Ware",
    "country": "Pakistan",
    "position": "Midfielder",
    "goals": 0,
    "assists": 2,
    "appearances": 15,
    "number": 32
  },
  {
    "fullName": "Elvis Armstrong",
    "country": "Chile",
    "position": "Midfielder",
    "goals": 2,
    "assists": 0,
    "appearances": 9,
    "number": 55
  },
  {
    "fullName": "Shelby Dillon",
    "country": "Poland",
    "position": "Midfielder",
    "goals": 1,
    "assists": 1,
    "appearances": 7,
    "number": 90
  },
  {
    "fullName": "Hunter Mendoza",
    "country": "Chile",
    "position": "Midfielder",
    "goals": 0,
    "assists": 1,
    "appearances": 3,
    "number": 86
  },
  {
    "fullName": "Genevieve Salinas",
    "country": "Canada",
    "position": "Midfielder",
    "goals": 1,
    "assists": 4,
    "appearances": 38,
    "number": 84
  },
  {
    "fullName": "Abraham Sanders",
    "country": "Germany",
    "position": "Midfielder",
    "goals": 1,
    "assists": 5,
    "appearances": 28,
    "number": 53
  },
  {
    "fullName": "Abra Roth",
    "country": "India",
    "position": "Midfielder",
    "goals": 3,
    "assists": 0,
    "appearances": 32,
    "number": 47
  },
  {
    "fullName": "Lunea Campos",
    "country": "Mexico",
    "position": "Midfielder",
    "goals": 0,
    "assists": 3,
    "appearances": 28,
    "number": 88
  },
  {
    "fullName": "Xantha Saunders",
    "country": "India",
    "position": "Forward",
    "goals": 0,
    "assists": 3,
    "appearances": 8,
    "number": 59
  },
  {
    "fullName": "Jorden Williamson",
    "country": "Chile",
    "position": "Forward",
    "goals": 1,
    "assists": 0,
    "appearances": 20,
    "number": 17
  },
  {
    "fullName": "Danielle Pace",
    "country": "Belgium",
    "position": "Forward",
    "goals": 2,
    "assists": 1,
    "appearances": 9,
    "number": 41
  },
  {
    "fullName": "Farrah Sawyer",
    "country": "Costa Rica",
    "position": "Forward",
    "goals": 2,
    "assists": 0,
    "appearances": 38,
    "number": 48
  },
  {
    "fullName": "Bevis Cobb",
    "country": "United Kingdom",
    "position": "Forward",
    "goals": 1,
    "assists": 2,
    "appearances": 17,
    "number": 54
  }
]
